combinational_ckt/full_adder/full_adder/full_adder.v
module full_adder(input a,b,cin, output s,cout);
    wire r1,w1,w2;
    xor x1(r1,a,b);
    xor x2(s,r1,cin);
    and a1(w1,a,b);
    and a2(w2,r1,cin);
    or o1(cout,w1,w2);
    
endmodule

combinational_ckt/full_adder/full_adder/tb.v
module tb();
    reg A_FA,B_FA,Cin_FA;
    wire S_FA,C_FA;
    full_adder fa1(.a(A_FA),.b(B_FA),.cin(Cin_FA),.s(S_FA),.cout(C_FA));

    initial begin
        $dumpfile("wave.vcd");
        $dumpvars(0, tb);
    end
    
    initial begin
        $display("A B C | S C");
        $monitor("%b %b %b | %b %b", A_FA, B_FA, Cin_FA,S_FA, C_FA);
        A_FA = 0; B_FA = 0; Cin_FA = 0;#10;
        A_FA = 0; B_FA = 0; Cin_FA = 1;#10;
        A_FA = 0; B_FA = 1; Cin_FA = 0;#10;
        A_FA = 0; B_FA = 1; Cin_FA = 1;#10;
        A_FA = 1; B_FA = 0; Cin_FA = 0;#10;
        A_FA = 1; B_FA = 0; Cin_FA = 1;#10;
        A_FA = 1; B_FA = 1; Cin_FA = 0;#10;
        A_FA = 1; B_FA = 1; Cin_FA = 1;#10;
        $finish;
    end

endmodule

combinational_ckt/full_adder/full_adder/wave.vcd
$date
	Sat Jun  6 00:40:21 2026
$end
$version
	Icarus Verilog
$end
$timescale
	1s
$end
$scope module tb $end
$var wire 1 ! S_FA $end
$var wire 1 " C_FA $end
$var reg 1 # A_FA $end
$var reg 1 $ B_FA $end
$var reg 1 % Cin_FA $end
$scope module fa1 $end
$var wire 1 # a $end
$var wire 1 $ b $end
$var wire 1 % cin $end
$var wire 1 " cout $end
$var wire 1 & r1 $end
$var wire 1 ! s $end
$var wire 1 ' w1 $end
$var wire 1 ( w2 $end
$upscope $end
$upscope $end
$enddefinitions $end
$comment Show the parameter values. $end
$dumpall
$end
#0
$dumpvars
0(
0'
0&
0%
0$
0#
0"
0!
$end
#10
1!
1%
#20
1&
0%
1$
#30
1"
0!
1(
1%
#40
0"
1!
0(
0%
0$
1#
#50
1"
0!
1(
1%
#60
0(
0&
1'
0%
1$
#70
1!
1%
