combinational_ckt/full_adder/full_adder_using_half_adder/full_adder.v
module half_adder(input A,B, output S,C);
    xor x1(S,A,B);
    and a1(C,A,B);
endmodule

module full_adder(input A,B,C_in,output S,C);
    wire W1,W2,W3;
    half_adder ha1(.A(A),.B(B),.S(W1),.C(W2));
    half_adder ha2(.A(W1),.B(C_in),.S(S),.C(W3));
    or o1(C,W2,W3);
endmodule

combinational_ckt/full_adder/full_adder_using_half_adder/tb.v
module tb();
    reg A_FA,B_FA,Cin_FA;
    wire S_FA,C_FA;
    full_adder fa1(.A(A_FA),.B(B_FA),.C_in(Cin_FA),.S(S_FA),.C(C_FA));

    initial begin
        $dumpfile("wave.vcd");
        $dumpvars(0, tb);
    end
    
    initial begin
        $display("A B C | S C");
        $monitor("%b %b %b | %b %b", A_FA, B_FA, Cin_FA,S_FA, C_FA);
        A_FA = 0; B_FA = 0; Cin_FA = 0;#10;
        A_FA = 0; B_FA = 0; Cin_FA = 1;#10;
        A_FA = 0; B_FA = 1; Cin_FA = 0;#10;
        A_FA = 0; B_FA = 1; Cin_FA = 1;#10;
        A_FA = 1; B_FA = 0; Cin_FA = 0;#10;
        A_FA = 1; B_FA = 0; Cin_FA = 1;#10;
        A_FA = 1; B_FA = 1; Cin_FA = 0;#10;
        A_FA = 1; B_FA = 1; Cin_FA = 1;#10;
        $finish;
    end

endmodule

combinational_ckt/full_adder/full_adder_using_half_adder/wave.vcd
$date
	Sat Jun  6 00:30:51 2026
$end
$version
	Icarus Verilog
$end
$timescale
	1s
$end
$scope module tb $end
$var wire 1 ! S_FA $end
$var wire 1 " C_FA $end
$var reg 1 # A_FA $end
$var reg 1 $ B_FA $end
$var reg 1 % Cin_FA $end
$scope module fa1 $end
$var wire 1 # A $end
$var wire 1 $ B $end
$var wire 1 " C $end
$var wire 1 % C_in $end
$var wire 1 & W3 $end
$var wire 1 ' W2 $end
$var wire 1 ( W1 $end
$var wire 1 ! S $end
$scope module ha1 $end
$var wire 1 # A $end
$var wire 1 $ B $end
$var wire 1 ' C $end
$var wire 1 ( S $end
$upscope $end
$scope module ha2 $end
$var wire 1 ( A $end
$var wire 1 % B $end
$var wire 1 & C $end
$var wire 1 ! S $end
$upscope $end
$upscope $end
$upscope $end
$enddefinitions $end
$comment Show the parameter values. $end
$dumpall
$end
#0
$dumpvars
0(
0'
0&
0%
0$
0#
0"
0!
$end
#10
1!
1%
#20
1(
0%
1$
#30
1"
0!
1&
1%
#40
0"
1!
0&
0%
0$
1#
#50
1"
0!
1&
1%
#60
0&
0(
1'
0%
1$
#70
1!
1%
